README.rst
setup.py
examscan.egg-info/PKG-INFO
examscan.egg-info/SOURCES.txt
examscan.egg-info/dependency_links.txt
examscan.egg-info/requires.txt
examscan.egg-info/top_level.txt
source/__init__.py
source/__main__.py
source/version.py
source/app/__init__.py
source/app/__main__.py
source/app/main.py
source/app/test.py
source/app/tkdnd.py
source/app/icon/icon.gif
source/app/icon/icon.ico
source/app/icon/icon.png
source/app/icon/icon.svg
source/demo/__init__.py
source/demo/__main__.py
source/demo/exam.pdf
source/demo/rooms.xlsx
source/demo/roster.xlsx
source/demo/scan.pdf
source/demo/settings.conf
source/demo/template.html
source/doc/__init__.py
source/doc/__main__.py
source/doc/examscan.pdf
source/scan/__init__.py
source/scan/__main__.py
source/scan/constants.py
source/scan/errors.py
source/scan/image_utils.py
source/scan/pdf.py
source/scan/qr_code.py
source/scan/report.py
source/scan/roster.py
source/scan/scorebox.py
source/scan/tickbox.py
source/scan/uin.py
source/tag/__init__.py
source/tag/__main__.py
source/tag/generate.py
source/tag/pdf.py
source/tag/seat.py
source/tmp/__init__.py
source/tmp/__main__.py
source/tmp/scandatabase.py