Metadata-Version: 1.0
Name: examscan
Version: 0.0.2
Summary: For added tags to and processing scanned exams.
Home-page: https://bitbucket.org/Mark_Bell/examscan
Author: Mark Bell
Author-email: mark00bell@googlemail.com
License: UNKNOWN
Platform: UNKNOWN
